pickle_data_file_utils/__init__.py
pickle_data_file_utils/csv2pickle.py
pickle_data_file_utils/file_utils.py
pickle_data_file_utils/generate_executables_and_aliases.py
pickle_data_file_utils/helper.py
pickle_data_file_utils/json2pickle.py
pickle_data_file_utils/pickle2csv.py
pickle_data_file_utils/pickle2json.py
pickle_data_file_utils/pickle2tsv.py
pickle_data_file_utils/tsv2pickle.py
pickle_data_file_utils-0.3.0.data/scripts/generate_executables_and_aliases.py
pickle_data_file_utils-0.3.0.dist-info/AUTHORS.rst
pickle_data_file_utils-0.3.0.dist-info/LICENSE
pickle_data_file_utils-0.3.0.dist-info/METADATA
pickle_data_file_utils-0.3.0.dist-info/WHEEL
pickle_data_file_utils-0.3.0.dist-info/entry_points.txt
pickle_data_file_utils-0.3.0.dist-info/top_level.txt
pickle_data_file_utils-0.3.0.dist-info/RECORD
